setup.py
lang/__init__.py
lang/abstract.py
lang/access.py
lang/exceptions.py
lang/experimental.py
lang/final.py
lang/interface.py
lang.egg-info/PKG-INFO
lang.egg-info/SOURCES.txt
lang.egg-info/dependency_links.txt
lang.egg-info/top_level.txt