Metadata-Version: 1.1
Name: lang
Version: 1.0.5
Summary: Module for enforcing language constraints in Python
Home-page: https://github.com/amitassaraf/lang
Author: Amit Assaraf
Author-email: soit48@gmail.com
License: APACHE
Keywords: lang language enforcing protected development
Platform: UNKNOWN
Classifier: Development Status :: 3 - Alpha
Classifier: Intended Audience :: Developers
Classifier: Topic :: Software Development :: Build Tools
Classifier: Programming Language :: Python :: 2
Classifier: Programming Language :: Python :: 2.6
Classifier: Programming Language :: Python :: 2.7
